Elf/__init__.py
Elf/elf_lookup.py
PE/__init__.py
PE/carve.py
PE/cofflib.py
PE/petool.py
PE/ordlookup/__init__.py
PE/ordlookup/comctl32.py
PE/ordlookup/mfc42.py
PE/ordlookup/msvbvm60.py
PE/ordlookup/oleaut32.py
PE/ordlookup/oledlg.py
PE/ordlookup/ws2_32.py
PE/tests/__init__.py
PE/tests/test_repr.py
PE/tests/test_version.py
PE/tools/__init__.py
PE/tools/printord.py
PE/tools/structdump.py
cobra/__init__.py
cobra/cache.py
cobra/cluster.py
cobra/dcode.py
cobra/devent.py
cobra/dispatcher.py
cobra/http.py
cobra/pool.py
cobra/remoteapp.py
cobra/auth/__init__.py
cobra/auth/shadowfile.py
cobra/hostid/__init__.py
cobra/hostid/darwinhostid.py
cobra/hostid/windowshostid.py
cobra/tests/__init__.py
cobra/tests/testbasic.py
cobra/tests/testcache.py
cobra/tests/testdcode.py
cobra/tests/testevents.py
cobra/tests/testnewobj.py
cobra/tools/__init__.py
cobra/tools/burnapp.py
cobra/tools/queend.py
cobra/tools/runtests.py
cobra/tools/workerd.py
envi/__init__.py
envi/bintree.py
envi/bits.py
envi/bytesig.py
envi/cli.py
envi/codeflow.py
envi/common.py
envi/config.py
envi/const.py
envi/encoding.py
envi/exc.py
envi/expression.py
envi/ieee754.py
envi/interactive.py
envi/memory.py
envi/pagelookup.py
envi/pyzip.py
envi/radixtree.py
envi/registers.py
envi/threads.py
envi/archs/__init__.py
envi/archs/aarch64/__init__.py
envi/archs/aarch64/const.py
envi/archs/aarch64/disasm.py
envi/archs/aarch64/emu.py
envi/archs/aarch64/regs.py
envi/archs/aarch64/regs_sys.py
envi/archs/aarch64/sysregs.py
envi/archs/amd64/__init__.py
envi/archs/amd64/disasm.py
envi/archs/amd64/opcode64.py
envi/archs/amd64/regs.py
envi/archs/amd64/vmcslookup.py
envi/archs/arm/__init__.py
envi/archs/arm/const.py
envi/archs/arm/disasm.py
envi/archs/arm/emu.py
envi/archs/arm/regs.py
envi/archs/h8/__init__.py
envi/archs/h8/const.py
envi/archs/h8/disasm.py
envi/archs/h8/emu.py
envi/archs/h8/operands.py
envi/archs/h8/parsers.py
envi/archs/h8/regs.py
envi/archs/i386/__init__.py
envi/archs/i386/disasm.py
envi/archs/i386/emu.py
vivisect-1.3.0.dist-info/licenses/LICENSE.txt
vivisect-1.3.0.dist-info/METADATA
vivisect-1.3.0.dist-info/WHEEL
vivisect-1.3.0.dist-info/entry_points.txt
vivisect-1.3.0.dist-info/top_level.txt
vivisect-1.3.0.dist-info/RECORD
